MANIFEST.in
README.rst
setup.py
docs/HISTORY.txt
docs/INSTALL.txt
docs/LICENSE.GPL
docs/LICENSE.txt
docs/TODO.txt
unice/.DS_Store
unice/__init__.py
unice.portlet.coordonnees.egg-info/PKG-INFO
unice.portlet.coordonnees.egg-info/SOURCES.txt
unice.portlet.coordonnees.egg-info/dependency_links.txt
unice.portlet.coordonnees.egg-info/entry_points.txt
unice.portlet.coordonnees.egg-info/namespace_packages.txt
unice.portlet.coordonnees.egg-info/not-zip-safe
unice.portlet.coordonnees.egg-info/requires.txt
unice.portlet.coordonnees.egg-info/top_level.txt
unice/portlet/.DS_Store
unice/portlet/__init__.py
unice/portlet/coordonnees/__init__.py
unice/portlet/coordonnees/configure.zcml
unice/portlet/coordonnees/coordonneesportlet.pt
unice/portlet/coordonnees/coordonneesportlet.py
unice/portlet/coordonnees/vocabularies.py
unice/portlet/coordonnees/browser/.DS_Store
unice/portlet/coordonnees/browser/__init__.py
unice/portlet/coordonnees/browser/configure.zcml
unice/portlet/coordonnees/browser/javascripts/scripts.js
unice/portlet/coordonnees/browser/stylesheets/styles.css
unice/portlet/coordonnees/profiles/.DS_Store
unice/portlet/coordonnees/profiles/default/cssregistry.xml
unice/portlet/coordonnees/profiles/default/jsregistry.xml
unice/portlet/coordonnees/profiles/default/metadata.xml
unice/portlet/coordonnees/profiles/default/portlets.xml
unice/portlet/coordonnees/tests/__init__.py
unice/portlet/coordonnees/tests/base.py
unice/portlet/coordonnees/tests/test_portlet.py